gme/__init__.py
gme/construct_data/DataLog.py
gme/construct_data/EstimationData.py
gme/construct_data/__init__.py
gme/construct_data/make_data_square.py
gme/estimate/DiagnosticsLog.py
gme/estimate/EstimationModel.py
gme/estimate/SlimResults.py
gme/estimate/Specification.py
gme/estimate/__init__.py
gme/estimate/_ppml_estimation_and_diagnostics.py
gme/estimate/_slice_data_for_estimation.py
gme/estimate/combine_sector_results.py
gme/estimate/format_regression_table.py
gme/estimate/save_and_load.py
gme/estimate/visualize_results.py
gme-1.3.1.dist-info/LICENSE.txt
gme-1.3.1.dist-info/METADATA
gme-1.3.1.dist-info/WHEEL
gme-1.3.1.dist-info/top_level.txt
gme-1.3.1.dist-info/RECORD
