Metadata-Version: 2.1
Name: gme
Version: 1.3.1
Summary: USITC Gravity Modeling Environment
Home-page: https://usitc-gravity-group.github.io/GME/
Author: USITC Gravity Modeling Group
Author-email: gravity@usitc.gov
Project-URL: Bug Tracker, https://github.com/USITC-Gravity-Group/GME/issues
Project-URL: Documentation, https://usitc-gravity-group.github.io/GME/
Classifier: Programming Language :: Python :: 3
Classifier: Operating System :: OS Independent
Classifier: License :: CC0 1.0 Universal (CC0 1.0) Public Domain Dedication
Requires-Python: >=3.7
License-File: LICENSE.txt
Requires-Dist: numpy>=1.19.2
Requires-Dist: scipy>=1.5.2
Requires-Dist: pandas>=1.1.2
Requires-Dist: matplotlib>=3.4.2
Requires-Dist: statsmodels>=0.12.2
